{
    "scaffolding_intro_text__bold": "Semua 298 penumpang dan awak di Malaysia Airlines tewas setelah pesawat jatuh di Ukraina timur di dekat perbatasan Rusia. Penerbangan MH17 dari Amsterdam ke Kuala Lumpur tanggal 17 Juli melintasi kawasan konflik dan pesawat jatuh ditembak.",
    "scaffolding_intro_text": "Amerika Serikat menuduh kelompok separatis pro-Rusia yang menembak pesawat dengan menggunakan rudal dan kemungkinan karena kesalahan yang bukan disengaja. Rusia menuduh pasukan pemerintah Ukraina. Seluruh korban jiwa berupa 283 penumpang -dengan 80 di antaranya anak-anak- dan 15 awak. Negara yang paling berkabung dengan jumlah korban terbesar adalah Belanda, diikuti Malaysia dan Australia.",
    "scaffolding_intro_cta": "Pilih gambar untuk mengetahui korban lebih jauh.",
    "scaffolding_graph_header": "Tentang korban",
    "scaffolding_graph_subheader": "Kebangsaan",
    "scaffolding_victims_total": "Jumlah total korban",
    "scaffolding_victims_male": "Pria",
    "scaffolding_victims_female": "Perempuan",
    "scaffolding_crew": "awak"
}